idream/__init__.py
idream/__main__.py
idream/schemas/idr-package-set.json
idream/schemas/idr-package.json
idream/schemas/idr-project.json
idream-0.1.1.dist-info/DESCRIPTION.rst
idream-0.1.1.dist-info/METADATA
idream-0.1.1.dist-info/RECORD
idream-0.1.1.dist-info/WHEEL
idream-0.1.1.dist-info/entry_points.txt
idream-0.1.1.dist-info/metadata.json
idream-0.1.1.dist-info/top_level.txt
